cfortune/__init__.py
cfortune/__main__.py
cfortune/cfortune.py
cfortune-0.0.2.dist-info/METADATA
cfortune-0.0.2.dist-info/RECORD
cfortune-0.0.2.dist-info/WHEEL
cfortune-0.0.2.dist-info/entry_points.txt
cfortune-0.0.2.dist-info/top_level.txt
