Metadata-Version: 2.1
Name: cfortune
Version: 0.0.2
Summary: Curses Fortune Browser
Home-page: https://github.com/tslight/cfortune
Author: Toby Slight
Author-email: tobyslight@gmail.com
License: UNKNOWN
Platform: UNKNOWN
Classifier: Programming Language :: Python :: 3
Classifier: License :: OSI Approved :: ISC License (ISCL)
Classifier: Operating System :: OS Independent
